{
  "hash": "10121eb9",
  "configHash": "2f80fd29",
  "lockfileHash": "19da3807",
  "browserHash": "42eb8b01",
  "optimized": {
    "react": {
      "src": "../../node_modules/react/index.js",
      "file": "react.js",
      "fileHash": "f4ef8db9",
      "needsInterop": true
    },
    "react-dom/client": {
      "src": "../../node_modules/react-dom/client.js",
      "file": "react-dom_client.js",
      "fileHash": "7e3bc82b",
      "needsInterop": true
    },
    "react-redux": {
      "src": "../../node_modules/react-redux/dist/react-redux.mjs",
      "file": "react-redux.js",
      "fileHash": "1786d69e",
      "needsInterop": false
    },
    "@tanstack/react-query": {
      "src": "../../node_modules/@tanstack/react-query/build/modern/index.js",
      "file": "@tanstack_react-query.js",
      "fileHash": "e9d55900",
      "needsInterop": false
    },
    "@reduxjs/toolkit": {
      "src": "../../node_modules/@reduxjs/toolkit/dist/redux-toolkit.modern.mjs",
      "file": "@reduxjs_toolkit.js",
      "fileHash": "77765ed7",
      "needsInterop": false
    },
    "react-router-dom": {
      "src": "../../node_modules/react-router-dom/dist/index.mjs",
      "file": "react-router-dom.js",
      "fileHash": "a62a6b75",
      "needsInterop": false
    },
    "react-toastify": {
      "src": "../../node_modules/react-toastify/dist/index.mjs",
      "file": "react-toastify.js",
      "fileHash": "dabfc96e",
      "needsInterop": false
    },
    "react-icons/fa": {
      "src": "../../node_modules/react-icons/fa/index.mjs",
      "file": "react-icons_fa.js",
      "fileHash": "1633d7ec",
      "needsInterop": false
    },
    "axios": {
      "src": "../../node_modules/axios/index.js",
      "file": "axios.js",
      "fileHash": "27e413b4",
      "needsInterop": false
    },
    "socket.io-client": {
      "src": "../../node_modules/socket.io-client/build/esm/index.js",
      "file": "socket__io-client.js",
      "fileHash": "e32ff7f1",
      "needsInterop": false
    }
  },
  "chunks": {
    "chunk-ECWOLUX3": {
      "file": "chunk-ECWOLUX3.js"
    },
    "chunk-Z4L4S4OG": {
      "file": "chunk-Z4L4S4OG.js"
    },
    "chunk-WOOG5QLI": {
      "file": "chunk-WOOG5QLI.js"
    }
  }
}